glorifiedgrep/__init__.py
glorifiedgrep/__version__.py
glorifiedgrep/logger.py
glorifiedgrep/out.py
glorifiedgrep/android/__init__.py
glorifiedgrep/android/modules/__init__.py
glorifiedgrep/android/modules/androidcore.py
glorifiedgrep/android/modules/certanalysis.py
glorifiedgrep/android/modules/codeanalysis.py
glorifiedgrep/android/modules/constants.py
glorifiedgrep/android/modules/exceptions.py
glorifiedgrep/android/modules/fileanalysis.py
glorifiedgrep/android/modules/malware.py
glorifiedgrep/android/modules/manifestanalysis.py
glorifiedgrep/android/modules/otheranalysis.py
glorifiedgrep/android/modules/owaspmasvs.py
glorifiedgrep/android/modules/reactapp.py
glorifiedgrep/android/modules/utils.py
glorifiedgrep-0.9.1.dist-info/LICENSE
glorifiedgrep-0.9.1.dist-info/METADATA
glorifiedgrep-0.9.1.dist-info/WHEEL
glorifiedgrep-0.9.1.dist-info/top_level.txt
glorifiedgrep-0.9.1.dist-info/RECORD
