Metadata-Version: 2.1
Name: glorifiedgrep
Version: 0.9.1
Summary: UNKNOWN
Home-page: UNKNOWN
Author: Hapsida @securisec
License: UNKNOWN
Platform: UNKNOWN
Classifier: Programming Language :: Python :: 3.7
Requires-Dist: ripgrepy
Requires-Dist: asn1crypto (==0.24.0)
Requires-Dist: cffi (==1.11.5)
Requires-Dist: cryptography (==2.3.1)
Requires-Dist: idna (==2.7)
Requires-Dist: javaobj-py3 (==0.2.4)
Requires-Dist: pyasn1-modules (==0.2.2)
Requires-Dist: pyasn1 (==0.4.4)
Requires-Dist: pycparser (==2.18)
Requires-Dist: pycryptodome (==3.6.6)
Requires-Dist: pyjks (==18.0.0)
Requires-Dist: pyopenssl (==18.0.0)
Requires-Dist: python-magic
Requires-Dist: six (==1.11.0)
Requires-Dist: twofish (==0.3.0)
Requires-Dist: xmltodict (==0.11.0)
